.gitignore
.pre-commit-config.yaml
CODE_OF_CONDUCT.md
CONTRIBUTING.md
LICENSE
MANIFEST.in
NOTICE
README.rst
setup.py
.github/workflows/docs.yml
.github/workflows/sphinx.yml
.github/workflows/testing.yml
aws/Dockerfile
aws/compile.sh
aws/docker-compose.yml
aws/handler.py
aws/push.sh
aws/requirements.txt
azcausal/__init__.py
azcausal/version.py
azcausal.egg-info/PKG-INFO
azcausal.egg-info/SOURCES.txt
azcausal.egg-info/dependency_links.txt
azcausal.egg-info/requires.txt
azcausal.egg-info/top_level.txt
azcausal/core/__init__.py
azcausal/core/data.py
azcausal/core/donors.py
azcausal/core/effect.py
azcausal/core/error.py
azcausal/core/estimator.py
azcausal/core/formating.py
azcausal/core/frame.py
azcausal/core/output.py
azcausal/core/panel.py
azcausal/core/parallelize.py
azcausal/core/regression.py
azcausal/core/result.py
azcausal/core/summary.py
azcausal/data/__init__.py
azcausal/estimators/__init__.py
azcausal/estimators/did.py
azcausal/estimators/event_study.py
azcausal/estimators/panel/__init__.py
azcausal/estimators/panel/did.py
azcausal/estimators/panel/fsdid.py
azcausal/estimators/panel/fuw.py
azcausal/estimators/panel/ratio.py
azcausal/estimators/panel/sdid.py
azcausal/estimators/panel/snn.py
azcausal/estimators/panel/vdid.py
azcausal/experimental/__init__.py
azcausal/experimental/outliers.py
azcausal/experimental/rdid.py
azcausal/experimental/rsdid.py
azcausal/experimental/snnb.py
azcausal/remote/__init__.py
azcausal/remote/client.py
azcausal/remote/job.py
azcausal/remote/serialization.py
azcausal/remote/server.py
azcausal/solvers/__init__.py
azcausal/solvers/solve_cvxpy.py
azcausal/solvers/solve_exception.py
azcausal/solvers/solve_grad.py
azcausal/solvers/solve_quad.py
azcausal/solvers/solve_scipy.py
azcausal/util/__init__.py
azcausal/util/analysis.py
azcausal/util/solver.py
docs/Makefile
docs/make.bat
docs/requirements.txt
docs/run_ipynb.py
docs/source/conf.py
docs/source/error.ipynb
docs/source/getting_started.ipynb
docs/source/index.rst
docs/source/installation.ipynb
docs/source/license.ipynb
docs/source/logo.ico
docs/source/logo.png
docs/source/logo.pptx
docs/source/parallelization.ipynb
docs/source/power.ipynb
