Metadata-Version: 2.1
Name: azcausal
Version: 0.2.4.2
Summary: Casual Inference
Home-page: https://github.com/amazon-science/azcausal
Author: Julian Blank
Author-email: blankjul@amazon.com
License: Apache License 2.0
Keywords: causality,inference
Platform: any
Classifier: Intended Audience :: Developers
Classifier: Intended Audience :: Science/Research
Classifier: Operating System :: OS Independent
Classifier: License :: OSI Approved :: Apache Software License
Classifier: Programming Language :: Python
Classifier: Programming Language :: Python :: 3
Classifier: Programming Language :: Python :: 3.7
Classifier: Programming Language :: Python :: 3.8
Classifier: Programming Language :: Python :: 3.9
Classifier: Programming Language :: Python :: 3.10
Classifier: Programming Language :: Python :: 3.11
Classifier: Topic :: Scientific/Engineering
Classifier: Topic :: Scientific/Engineering :: Artificial Intelligence
Classifier: Topic :: Scientific/Engineering :: Mathematics
Requires-Python: >=3.7
Provides-Extra: snnb
Provides-Extra: aws
Provides-Extra: snn
Provides-Extra: core
Provides-Extra: fsdid
Provides-Extra: full
License-File: LICENSE
License-File: NOTICE
